odoo/addons/importar_lineas_pedido/.gitignore
odoo/addons/importar_lineas_pedido/CHANGELOG.md
odoo/addons/importar_lineas_pedido/LICENSE
odoo/addons/importar_lineas_pedido/Readme.md
odoo/addons/importar_lineas_pedido/__init__.py
odoo/addons/importar_lineas_pedido/__manifest__.py
odoo/addons/importar_lineas_pedido/Sample Files/sale_order_line.xlsx
odoo/addons/importar_lineas_pedido/controllers/__init__.py
odoo/addons/importar_lineas_pedido/controllers/download_xls.py
odoo/addons/importar_lineas_pedido/data/attachment_sample.xml
odoo/addons/importar_lineas_pedido/i18n/es.po
odoo/addons/importar_lineas_pedido/security/ir.model.access.csv
odoo/addons/importar_lineas_pedido/views/importar_lineas_pedido_view.xml
odoo/addons/importar_lineas_pedido/wizards/__init__.py
odoo/addons/importar_lineas_pedido/wizards/importar_lineas_pedido.py
odoo_addon_importar_lineas_pedido-17.0.1.1.3.dist-info/METADATA
odoo_addon_importar_lineas_pedido-17.0.1.1.3.dist-info/WHEEL
odoo_addon_importar_lineas_pedido-17.0.1.1.3.dist-info/top_level.txt
odoo_addon_importar_lineas_pedido-17.0.1.1.3.dist-info/RECORD
